dlmhelper/__init__.py
dlmhelper/data.py
dlmhelper/spatio_temporal.py
dlmhelper/tools.py
dlmhelper-1.0.0.dist-info/METADATA
dlmhelper-1.0.0.dist-info/WHEEL
dlmhelper-1.0.0.dist-info/licenses/LICENSE
dlmhelper-1.0.0.dist-info/RECORD
