Metadata-Version: 2.4
Name: dlmhelper
Version: 1.0.0
Summary: This package includes functions and custom data types to help with performing dynamic linear model fits and analyzing the results.
Project-URL: Homepage, https://github.com/JonasHach/dlmhelper
Project-URL: Bug Tracker, https://github.com/JonasHach/dlmhelper/issues
Author-email: Jonas Hachmeister <jonas.hachmeister@posteo.de>
License-File: LICENSE
Classifier: License :: OSI Approved :: GNU General Public License v3 (GPLv3)
Classifier: Operating System :: OS Independent
Classifier: Programming Language :: Python :: 3
Classifier: Topic :: Scientific/Engineering :: Physics
Requires-Python: >=3.8
Requires-Dist: matplotlib>=3.5
Requires-Dist: numpy>=1.22
Requires-Dist: statsmodels>=0.13
Requires-Dist: tabulate>=0.9
